meta_labs/__init__.py
meta_labs/admin.py
meta_labs/aliquot_types.py
meta_labs/apps.py
meta_labs/lab_profiles.py
meta_labs/labs.py
meta_labs/list_data.py
meta_labs/panels.py
meta_labs/processing_profiles.py
meta_labs/reportables.py
meta_labs/tests/__init__.py
meta_labs/tests/test_labs.py
meta_labs/tests/test_reportables.py
meta_labs/tests/urls.py
meta_labs-0.1.11.dist-info/LICENSE
meta_labs-0.1.11.dist-info/METADATA
meta_labs-0.1.11.dist-info/WHEEL
meta_labs-0.1.11.dist-info/top_level.txt
meta_labs-0.1.11.dist-info/RECORD
